{
  "theme": {
    "$description": "Dark theme semantic tokens",
    "color": {
      "background": {
        "default": {
          "$value": "{color.dark.900}",
          "$type": "color",
          "$description": "Default page background"
        },
        "subtle": {
          "$value": "{color.dark.800}",
          "$type": "color",
          "$description": "Subtle background for sections"
        },
        "muted": {
          "$value": "{color.dark.700}",
          "$type": "color",
          "$description": "Muted background for disabled states"
        }
      },
      "surface": {
        "default": {
          "$value": "{color.dark.800}",
          "$type": "color",
          "$description": "Default surface color for cards, modals"
        },
        "subtle": {
          "$value": "{color.dark.700}",
          "$type": "color",
          "$description": "Subtle surface variation"
        },
        "hover": {
          "$value": "{color.dark.600}",
          "$type": "color",
          "$description": "Surface hover state"
        }
      },
      "border": {
        "default": {
          "$value": "{color.dark.600}",
          "$type": "color",
          "$description": "Default border color"
        },
        "subtle": {
          "$value": "{color.dark.700}",
          "$type": "color",
          "$description": "Subtle border color"
        },
        "strong": {
          "$value": "{color.dark.400}",
          "$type": "color",
          "$description": "Strong border color"
        }
      },
      "text": {
        "default": {
          "$value": "{color.dark.50}",
          "$type": "color",
          "$description": "Default text color"
        },
        "subtle": {
          "$value": "{color.dark.100}",
          "$type": "color",
          "$description": "Subtle text color"
        },
        "muted": {
          "$value": "{color.dark.300}",
          "$type": "color",
          "$description": "Muted text color"
        },
        "disabled": {
          "$value": "{color.dark.600}",
          "$type": "color",
          "$description": "Disabled text color"
        },
        "inverse": {
          "$value": "{color.black}",
          "$type": "color",
          "$description": "Inverse text color"
        }
      },
      "primary": {
        "default": {
          "$value": "{color.blue.500}",
          "$type": "color",
          "$description": "Primary brand color"
        },
        "hover": {
          "$value": "{color.blue.400}",
          "$type": "color",
          "$description": "Primary hover state"
        },
        "active": {
          "$value": "{color.blue.300}",
          "$type": "color",
          "$description": "Primary active/pressed state"
        },
        "subtle": {
          "$value": "rgba(74, 144, 226, 0.15)",
          "$type": "color",
          "$description": "Primary subtle background"
        },
        "subtleHover": {
          "$value": "rgba(74, 144, 226, 0.25)",
          "$type": "color",
          "$description": "Primary subtle hover"
        },
        "contrast": {
          "$value": "{color.white}",
          "$type": "color",
          "$description": "Contrast color on primary"
        }
      },
      "success": {
        "default": {
          "$value": "{color.green.500}",
          "$type": "color",
          "$description": "Success state color"
        },
        "subtle": {
          "$value": "rgba(64, 192, 87, 0.15)",
          "$type": "color",
          "$description": "Success subtle background"
        },
        "contrast": {
          "$value": "{color.white}",
          "$type": "color"
        }
      },
      "warning": {
        "default": {
          "$value": "{color.yellow.500}",
          "$type": "color",
          "$description": "Warning state color"
        },
        "subtle": {
          "$value": "rgba(252, 196, 25, 0.15)",
          "$type": "color",
          "$description": "Warning subtle background"
        },
        "contrast": {
          "$value": "{color.black}",
          "$type": "color"
        }
      },
      "error": {
        "default": {
          "$value": "{color.red.500}",
          "$type": "color",
          "$description": "Error state color"
        },
        "subtle": {
          "$value": "rgba(250, 82, 82, 0.15)",
          "$type": "color",
          "$description": "Error subtle background"
        },
        "contrast": {
          "$value": "{color.white}",
          "$type": "color"
        }
      },
      "info": {
        "default": {
          "$value": "{color.blue.500}",
          "$type": "color",
          "$description": "Info state color"
        },
        "subtle": {
          "$value": "rgba(74, 144, 226, 0.15)",
          "$type": "color",
          "$description": "Info subtle background"
        },
        "contrast": {
          "$value": "{color.white}",
          "$type": "color"
        }
      }
    }
  }
}